pytest_annotated.py
pytest_annotated-0.1.1.dist-info/LICENSE
pytest_annotated-0.1.1.dist-info/METADATA
pytest_annotated-0.1.1.dist-info/WHEEL
pytest_annotated-0.1.1.dist-info/entry_points.txt
pytest_annotated-0.1.1.dist-info/top_level.txt
pytest_annotated-0.1.1.dist-info/RECORD
