Metadata-Version: 2.1
Name: pytest-annotated
Version: 0.1.1
Summary: Pytest plugin to allow use of Annotated in tests to resolve fixtures
Author-email: Tristan King <git@tristan.sh>
Project-URL: Homepage, https://github.com/tristan/pytest-annotated
Project-URL: Issues, https://github.com/tristan/pytest-annotated/issues
Classifier: Programming Language :: Python :: 3
Classifier: License :: OSI Approved :: MIT License
Classifier: Operating System :: OS Independent
Requires-Python: >=3.10
License-File: LICENSE
Requires-Dist: pytest >=8.3.3
